{"cameraMode":{"drawMode":0,"name":"Shaded","section":"Shading Mode"},"sceneLighting":false,"audioPlay":false,"sceneViewState":{"m_AlwaysRefresh":false,"showFog":true,"showSkybox":false,"showFlares":true,"showImageEffects":true,"showParticleSystems":true,"showVisualEffectGraphs":true,"m_FxEnabled":true},"in2DMode":false,"pivot":{"x":-5.783156394958496,"y":-11.670629501342774,"z":60.1813850402832},"rotation":{"x":-0.20607884228229524,"y":0.01685585454106331,"z":-0.003550786292180419,"w":-0.9784265756607056},"size":20.563068389892579,"orthographic":false}